brain_indexer/__init__.py
brain_indexer/_brain_indexer.cpython-310-x86_64-linux-gnu.so
brain_indexer/builder.py
brain_indexer/chunked_builder.py
brain_indexer/commands.py
brain_indexer/experimental.py
brain_indexer/index.py
brain_indexer/io.py
brain_indexer/logging_settings.py
brain_indexer/morphology_builder.py
brain_indexer/resolver.py
brain_indexer/synapse_builder.py
brain_indexer/synthetic_index.py
brain_indexer/util.py
brain_indexer.libs/libboost_serialization-c0773b32.so.1.85.0
brain_indexer-3.1.1.dist-info/METADATA
brain_indexer-3.1.1.dist-info/WHEEL
brain_indexer-3.1.1.dist-info/entry_points.txt
brain_indexer-3.1.1.dist-info/RECORD
brain_indexer-3.1.1.dist-info/licenses/AUTHORS.txt
brain_indexer-3.1.1.dist-info/licenses/LICENSE.txt
