Metadata-Version: 2.4
Name: brain-indexer
Version: 3.1.1
Summary: A spatial index implementation for spheres, morphologies and synapses
Author-Email: Blue Brain Project <bbp-ou-hpc@epfl.ch>
Maintainer: Fernando Pereira, Antonio Bellotta, Luc Dominic Grosheintz-Laval
License-Expression: Apache-2.0
License-File: LICENSE.txt
Classifier: Development Status :: 3 - Alpha
Classifier: Programming Language :: C++
Classifier: Programming Language :: Python
Classifier: Topic :: Scientific/Engineering
Project-URL: Repository, https://github.com/BlueBrain/brain-indexer.git
Project-URL: Tracker, https://github.com/BlueBrain/brain-indexer/issues
Project-URL: Homepage, https://github.com/BlueBrain/brain-indexer
Requires-Python: >=3.9
Requires-Dist: numpy>=1.13.1
Requires-Dist: numpy-quaternion
Requires-Dist: libsonata!=0.1.15
Requires-Dist: morphio
Requires-Dist: docopt-ng
Requires-Dist: tqdm
Provides-Extra: mpi
Requires-Dist: mpi4py; extra == "mpi"
